src/counter4.v
`timescale 1ns/1ps
module counter4(input wire clk,rst,enable,down,output reg [3:0] value);
always @(posedge clk) if(rst) value<=0; else if(enable) begin
if(down) value<=value-4'd1; else value<=value+4'd1; end
endmodule

sim/tb_counter4.sv
`timescale 1ns/1ps
module tb_counter4;
reg clk=0,rst=1;integer checks=0;always #5 clk=~clk;
task step;begin @(posedge clk);#1;end endtask
task check(input condition,input [8*100-1:0] description);begin
checks=checks+1;if(condition!==1'b1) begin $display("LAB2_FAIL %0s time=%0t",description,$time);$fatal(1,"check failed");end end endtask
initial begin #100000;$fatal(1,"watchdog timeout");end
reg enable=0,down=0;wire [3:0] value;integer i;
counter4 dut(clk,rst,enable,down,value);
initial begin $dumpfile("wave.vcd");$dumpvars(0,tb_counter4);end
initial begin
step;check(value===0,"reset");rst=0;enable=1;
for(i=1;i<=16;i=i+1) begin step;check(value===(i%16),"up including 15 to 0");end
down=1;for(i=15;i>=0;i=i-1) begin step;check(value===i,"down including 0 to 15");end
enable=0;step;check(value===0,"hold");enable=1;step;check(value===15,"down wrap");
rst=1;step;check(value===0,"reset beats enable");
$display("LAB2_PASS counter4 checks=%0d",checks);$display("END_NS=%0d",$time);$finish;end
endmodule

evidence/vscode/normal_wave.vcd
$date
	Sun Sep 20 17:17:48 2026
$end
$version
	Icarus Verilog
$end
$timescale
	1ps
$end
$scope module tb_counter4 $end
$var wire 4 ! value [3:0] $end
$var reg 1 " clk $end
$var reg 1 # down $end
$var reg 1 $ enable $end
$var reg 1 % rst $end
$var integer 32 & checks [31:0] $end
$var integer 32 ' i [31:0] $end
$scope module dut $end
$var wire 1 " clk $end
$var wire 1 # down $end
$var wire 1 $ enable $end
$var wire 1 % rst $end
$var reg 4 ( value [3:0] $end
$upscope $end
$scope task check $end
$var reg 1 ) condition $end
$var reg 800 * description [799:0] $end
$upscope $end
$scope task step $end
$upscope $end
$upscope $end
$enddefinitions $end
$comment Show the parameter values. $end
$dumpall
$end
#0
$dumpvars
bx *
x)
bx (
bx '
b0 &
1%
0$
0#
0"
bx !
$end
#5000
b0 !
b0 (
1"
#6000
b1 '
1$
0%
b1 &
b111001001100101011100110110010101110100 *
1)
#10000
0"
#15000
b1 !
b1 (
1"
#16000
b10 '
b10 &
b111010101110000001000000110100101101110011000110110110001110101011001000110100101101110011001110010000000110001001101010010000001110100011011110010000000110000 *
#20000
0"
#25000
b10 !
b10 (
1"
#26000
b11 '
b11 &
#30000
0"
#35000
b11 !
b11 (
1"
#36000
b100 '
b100 &
#40000
0"
#45000
b100 !
b100 (
1"
#46000
b101 '
b101 &
#50000
0"
#55000
b101 !
b101 (
1"
#56000
b110 '
b110 &
#60000
0"
#65000
b110 !
b110 (
1"
#66000
b111 '
b111 &
#70000
0"
#75000
b111 !
b111 (
1"
#76000
b1000 '
b1000 &
#80000
0"
#85000
b1000 !
b1000 (
1"
#86000
b1001 '
b1001 &
#90000
0"
#95000
b1001 !
b1001 (
1"
#96000
b1010 '
b1010 &
#100000
0"
#105000
b1010 !
b1010 (
1"
#106000
b1011 '
b1011 &
#110000
0"
#115000
b1011 !
b1011 (
1"
#116000
b1100 '
b1100 &
#120000
0"
#125000
b1100 !
b1100 (
1"
#126000
b1101 '
b1101 &
#130000
0"
#135000
b1101 !
b1101 (
1"
#136000
b1110 '
b1110 &
#140000
0"
#145000
b1110 !
b1110 (
1"
#146000
b1111 '
b1111 &
#150000
0"
#155000
b1111 !
b1111 (
1"
#156000
b10000 '
b10000 &
#160000
0"
#165000
b0 !
b0 (
1"
#166000
1#
b1111 '
b10001 &
#170000
0"
#175000
b1111 !
b1111 (
1"
#176000
b1110 '
b10010 &
b1100100011011110111011101101110001000000110100101101110011000110110110001110101011001000110100101101110011001110010000000110000001000000111010001101111001000000011000100110101 *
#180000
0"
#185000
b1110 !
b1110 (
1"
#186000
b1101 '
b10011 &
#190000
0"
#195000
b1101 !
b1101 (
1"
#196000
b1100 '
b10100 &
#200000
0"
#205000
b1100 !
b1100 (
1"
#206000
b1011 '
b10101 &
#210000
0"
#215000
b1011 !
b1011 (
1"
#216000
b1010 '
b10110 &
#220000
0"
#225000
b1010 !
b1010 (
1"
#226000
b1001 '
b10111 &
#230000
0"
#235000
b1001 !
b1001 (
1"
#236000
b1000 '
b11000 &
#240000
0"
#245000
b1000 !
b1000 (
1"
#246000
b111 '
b11001 &
#250000
0"
#255000
b111 !
b111 (
1"
#256000
b110 '
b11010 &
#260000
0"
#265000
b110 !
b110 (
1"
#266000
b101 '
b11011 &
#270000
0"
#275000
b101 !
b101 (
1"
#276000
b100 '
b11100 &
#280000
0"
#285000
b100 !
b100 (
1"
#286000
b11 '
b11101 &
#290000
0"
#295000
b11 !
b11 (
1"
#296000
b10 '
b11110 &
#300000
0"
#305000
b10 !
b10 (
1"
#306000
b1 '
b11111 &
#310000
0"
#315000
b1 !
b1 (
1"
#316000
b0 '
b100000 &
#320000
0"
#325000
b0 !
b0 (
1"
#326000
0$
b11111111111111111111111111111111 '
b100001 &
#330000
0"
#335000
1"
#336000
1$
b100010 &
b1101000011011110110110001100100 *
#340000
0"
#345000
b1111 !
b1111 (
1"
#346000
1%
b100011 &
b11001000110111101110111011011100010000001110111011100100110000101110000 *
#350000
0"
#355000
b0 !
b0 (
1"
#356000
b100100 &
b11100100110010101110011011001010111010000100000011000100110010101100001011101000111001100100000011001010110111001100001011000100110110001100101 *
